rshiny_server_cmd/__init__.py
rshiny_server_cmd/main.py
rshiny_server_cmd-0.0.2.dist-info/LICENSE
rshiny_server_cmd-0.0.2.dist-info/METADATA
rshiny_server_cmd-0.0.2.dist-info/WHEEL
rshiny_server_cmd-0.0.2.dist-info/entry_points.txt
rshiny_server_cmd-0.0.2.dist-info/top_level.txt
rshiny_server_cmd-0.0.2.dist-info/RECORD
