Metadata-Version: 2.1
Name: rshiny-server-cmd
Version: 0.0.2
Summary: Command line wrapper to run an R Shiny Server
Home-page: https://github.com/ideonate/rshiny-server-cmd
Author: Dan Lester
Author-email: dan@ideonate.com
License: UNKNOWN
Platform: UNKNOWN
Classifier: Programming Language :: Python :: 3
Classifier: License :: OSI Approved :: MIT License
Classifier: Operating System :: OS Independent
Requires-Python: >=3.6
Requires-Dist: Click (>=7.0)
